cmds/__init__.py
cmds/analyse.py
cmds/crawl.py
cmds/entry.py
crawler/__init__.py
crawler/crawler.py
crawler/pipelines.py
crawler/spider.py
ranker/__init__.py
ranker/ranker.py
rasis-0.1.0.dist-info/METADATA
rasis-0.1.0.dist-info/RECORD
rasis-0.1.0.dist-info/WHEEL
rasis-0.1.0.dist-info/entry_points.txt
rasis-0.1.0.dist-info/top_level.txt
