Metadata-Version: 2.1
Name: rasis
Version: 0.1.0
Summary: UNKNOWN
Home-page: UNKNOWN
Author: UNKNOWN
Author-email: UNKNOWN
License: UNKNOWN
Platform: UNKNOWN
Requires-Dist: Click
Requires-Dist: scrapy
Requires-Dist: scrapy-splash
Requires-Dist: pandas
Requires-Dist: Pillow
